hd1codeplug/__init__.py
hd1codeplug/codeplug.py
hd1codeplug-0.9.3.dist-info/LICENSE
hd1codeplug-0.9.3.dist-info/METADATA
hd1codeplug-0.9.3.dist-info/WHEEL
hd1codeplug-0.9.3.dist-info/top_level.txt
hd1codeplug-0.9.3.dist-info/RECORD
